README.rst
bencode.py
setup.cfg
setup.py
bencode_parser.egg-info/PKG-INFO
bencode_parser.egg-info/SOURCES.txt
bencode_parser.egg-info/dependency_links.txt
bencode_parser.egg-info/not-zip-safe
bencode_parser.egg-info/requires.txt
bencode_parser.egg-info/top_level.txt