Metadata-Version: 1.0
Name: bencode-parser
Version: 1.0.1
Summary: Library that encodes/decodes bencode formated strings topython objects.
Home-page: https://github.com/huseyinyilmaz/python-bencode
Author: Huseyin Yilmaz
Author-email: yilmazhuseyin@gmail.com
License: UNKNOWN
Platform: UNKNOWN
